src/__init__.py
src/matadd.py
src/matmul.py
src/matsub.py
alg_mat-0.0.1.dist-info/LICENSE
alg_mat-0.0.1.dist-info/METADATA
alg_mat-0.0.1.dist-info/WHEEL
alg_mat-0.0.1.dist-info/top_level.txt
alg_mat-0.0.1.dist-info/RECORD
