Metadata-Version: 2.1
Name: alg-mat
Version: 0.0.1
Summary: Basic Matrix algebra
Author: ADITYA PANAYAL
Author-email: adpanayal@gmail.com
Classifier: Programming Language :: Python :: 3
Classifier: License :: OSI Approved :: MIT License
Classifier: Operating System :: OS Independent
License-File: LICENSE
